odoo/addons/request_document_tier_validation/README.rst
odoo/addons/request_document_tier_validation/__init__.py
odoo/addons/request_document_tier_validation/__manifest__.py
odoo/addons/request_document_tier_validation/i18n/request_document_tier_validation.pot
odoo/addons/request_document_tier_validation/models/__init__.py
odoo/addons/request_document_tier_validation/models/request_order.py
odoo/addons/request_document_tier_validation/models/tier_definition.py
odoo/addons/request_document_tier_validation/readme/CONTRIBUTORS.rst
odoo/addons/request_document_tier_validation/readme/DESCRIPTION.rst
odoo/addons/request_document_tier_validation/static/description/icon.png
odoo/addons/request_document_tier_validation/static/description/index.html
odoo/addons/request_document_tier_validation/tests/__init__.py
odoo/addons/request_document_tier_validation/tests/test_request_document_tier_validation.py
odoo_addon_request_document_tier_validation-18.0.1.0.0.2.dist-info/METADATA
odoo_addon_request_document_tier_validation-18.0.1.0.0.2.dist-info/WHEEL
odoo_addon_request_document_tier_validation-18.0.1.0.0.2.dist-info/top_level.txt
odoo_addon_request_document_tier_validation-18.0.1.0.0.2.dist-info/RECORD
